COPYING
MANIFEST.in
README.rst
bootstrap.py
buildout.cfg
setup.py
xbob/__init__.py
xbob.paper.BTFS2013.egg-info/PKG-INFO
xbob.paper.BTFS2013.egg-info/SOURCES.txt
xbob.paper.BTFS2013.egg-info/dependency_links.txt
xbob.paper.BTFS2013.egg-info/entry_points.txt
xbob.paper.BTFS2013.egg-info/namespace_packages.txt
xbob.paper.BTFS2013.egg-info/not-zip-safe
xbob.paper.BTFS2013.egg-info/requires.txt
xbob.paper.BTFS2013.egg-info/top_level.txt
xbob/paper/__init__.py
xbob/paper/BTFS2013/__init__.py
xbob/paper/BTFS2013/bimodal.py
xbob/paper/BTFS2013/plots.py
xbob/paper/BTFS2013/single.py
xbob/paper/BTFS2013/unimodal.py
xbob/paper/BTFS2013/utils.py