Metadata-Version: 1.1
Name: xbob.paper.BTFS2013
Version: 1.0.0
Summary: On the Improvements of Uni-modal and Bi-modal Fusions of Speaker and Face Recognition for Mobile Biometrics
Home-page: http://gitlab.idiap.ch/manuel.guenther/xbob-paper-BTFS2013
Author: Manuel Guenther
Author-email: manuel.guenther@idiap.ch
License: GPLv3
Keywords: face recognition,speaker recognition,fusion,uni-modal,bi-modal,bob,xbob,MOBIO
Platform: UNKNOWN
Classifier: Development Status :: 4 - Beta
Classifier: Environment :: Console
Classifier: Intended Audience :: Developers
Classifier: Intended Audience :: Education
Classifier: Intended Audience :: Science/Research
Classifier: License :: OSI Approved :: GNU General Public License v3 (GPLv3)
Classifier: Natural Language :: English
Classifier: Programming Language :: Python
Classifier: Programming Language :: Python :: 3
Classifier: Topic :: Scientific/Engineering :: Artificial Intelligence
